stimulant/__init__.py
stimulant/_cli.py
stimulant/_stimulant.py
stimulant-1.0.1.dist-info/LICENSE
stimulant-1.0.1.dist-info/METADATA
stimulant-1.0.1.dist-info/WHEEL
stimulant-1.0.1.dist-info/entry_points.txt
stimulant-1.0.1.dist-info/top_level.txt
stimulant-1.0.1.dist-info/RECORD
