Metadata-Version: 2.1
Name: stimulant
Version: 1.0.1
Summary: Keeps the screen awake by moving the mouse randomly
Author-email: Sid Ganti <gantisid@gmail.com>
Maintainer-email: Sid Ganti <gantisid@gmail.com>
License: Mozilla Public License Version 2.0
Project-URL: Homepage, https://github.com/sidganti/stimulant
Project-URL: Documentation, https://github.com/sidganti/stimulant/blob/main/README.md
Project-URL: Repository, https://github.com/sidganti/stimulant.git
Project-URL: Issues, https://github.com/sidganti/stimulant/issues
Classifier: Programming Language :: Python :: 3
Classifier: License :: OSI Approved :: MIT License
Classifier: Operating System :: OS Independent
Requires-Python: >=3.12
License-File: LICENSE
Requires-Dist: PyAutoGUI ==0.9.54
